unihan_etl/__about__.py
unihan_etl/__init__.py
unihan_etl/__main__.py
unihan_etl/constants.py
unihan_etl/core.py
unihan_etl/expansion.py
unihan_etl/options.py
unihan_etl/py.typed
unihan_etl/pytest_plugin.py
unihan_etl/test.py
unihan_etl/types.py
unihan_etl/util.py
unihan_etl/_internal/__init__.py
unihan_etl/_internal/app_dirs.py
unihan_etl/_internal/private_path.py
unihan_etl/cli/__init__.py
unihan_etl/cli/_colors.py
unihan_etl/cli/_formatter.py
unihan_etl/cli/_output.py
unihan_etl/cli/download.py
unihan_etl/cli/export.py
unihan_etl/cli/fields.py
unihan_etl/cli/files.py
unihan_etl/cli/search.py
unihan_etl/data_files/quick/Unihan_DictionaryIndices.txt
unihan_etl/data_files/quick/Unihan_DictionaryLikeData.txt
unihan_etl/data_files/quick/Unihan_IRGSources.txt
unihan_etl/data_files/quick/Unihan_NumericValues.txt
unihan_etl/data_files/quick/Unihan_OtherMappings.txt
unihan_etl/data_files/quick/Unihan_RadicalStrokeCounts.txt
unihan_etl/data_files/quick/Unihan_Readings.txt
unihan_etl/data_files/quick/Unihan_Variants.txt
unihan_etl-0.40.0.dist-info/METADATA
unihan_etl-0.40.0.dist-info/WHEEL
unihan_etl-0.40.0.dist-info/entry_points.txt
unihan_etl-0.40.0.dist-info/licenses/LICENSE
unihan_etl-0.40.0.dist-info/RECORD
