Metadata-Version: 2.4
Name: unihan-etl
Version: 0.40.0
Summary: Export UNIHAN data of Chinese, Japanese, Korean to CSV, JSON or YAML
Project-URL: Bug Tracker, https://github.com/cihai/unihan-etl/issues
Project-URL: Documentation, https://unihan-etl.git-pull.com
Project-URL: Repository, https://github.com/cihai/unihan-etl
Project-URL: Changes, https://github.com/cihai/unihan-etl/blob/master/CHANGES
Author-email: Tony Narlock <tony@git-pull.com>
License: MIT
License-File: LICENSE
Keywords: chinese,cjk,dataset,dictionary,hanzi,japanese,json,korean,unicode,unihan,yaml
Classifier: Development Status :: 4 - Beta
Classifier: Environment :: Web Environment
Classifier: Intended Audience :: Developers
Classifier: License :: OSI Approved :: MIT License
Classifier: Programming Language :: Python
Classifier: Programming Language :: Python :: 3
Classifier: Programming Language :: Python :: 3.10
Classifier: Programming Language :: Python :: 3.11
Classifier: Programming Language :: Python :: 3.12
Classifier: Programming Language :: Python :: 3.13
Classifier: Programming Language :: Python :: 3.14
Classifier: Programming Language :: Python :: Implementation :: PyPy
Classifier: Topic :: Software Development :: Internationalization
Classifier: Topic :: Software Development :: Localization
Classifier: Topic :: Utilities
Classifier: Typing :: Typed
Requires-Python: <4.0,>=3.10
Requires-Dist: appdirs
Requires-Dist: pyyaml
Requires-Dist: unicodecsv
Requires-Dist: zhon~=2.0
